setup.py
v_ease_probab/Binomialdistribution.py
v_ease_probab/Gaussiandistribution.py
v_ease_probab/Generaldistribution.py
v_ease_probab/__init__.py
v_ease_probab.egg-info/PKG-INFO
v_ease_probab.egg-info/SOURCES.txt
v_ease_probab.egg-info/dependency_links.txt
v_ease_probab.egg-info/not-zip-safe
v_ease_probab.egg-info/top_level.txt