Metadata-Version: 1.0
Name: v-ease-probab
Version: 0.0.1
Summary: Gaussian distributions
Home-page: UNKNOWN
Author: Soheb
Author-email: sksoheb54@gmail.com
License: UNKNOWN
Platform: UNKNOWN
